secretverify/__init__.py
secretverify/cli.py
secretverify/validators.py
secretverify-0.7.0.dist-info/METADATA
secretverify-0.7.0.dist-info/WHEEL
secretverify-0.7.0.dist-info/entry_points.txt
secretverify-0.7.0.dist-info/top_level.txt
secretverify-0.7.0.dist-info/RECORD
