Metadata-Version: 2.4
Name: secretverify
Version: 0.7.0
Summary: Terminal-based tool to quickly validate leaked secrets across multiple providers.
Home-page: https://github.com/markgraziano-twlo/secretverify
Author: Mark Graziano
Author-email: mgraziano@twilio.com
License: MIT
Classifier: Programming Language :: Python :: 3
Classifier: License :: OSI Approved :: MIT License
Classifier: Operating System :: OS Independent
Requires-Python: >=3.10
Requires-Dist: click>=8.1.7
Requires-Dist: requests>=2.31.0
Requires-Dist: boto3>=1.26.151
Requires-Dist: google-auth>=2.23.0
Dynamic: author
Dynamic: author-email
Dynamic: classifier
Dynamic: description
Dynamic: description-content-type
Dynamic: home-page
Dynamic: license
Dynamic: requires-dist
Dynamic: requires-python
Dynamic: summary
